dash_mqtt/DashMqtt.py
dash_mqtt/__init__.py
dash_mqtt/_imports_.py
dash_mqtt/dash_mqtt.min.js
dash_mqtt/dash_mqtt.min.js.map
dash_mqtt/metadata.json
dash_mqtt/package-info.json
dash_mqtt-0.0.2.dist-info/LICENSE
dash_mqtt-0.0.2.dist-info/METADATA
dash_mqtt-0.0.2.dist-info/WHEEL
dash_mqtt-0.0.2.dist-info/top_level.txt
dash_mqtt-0.0.2.dist-info/RECORD
