Metadata-Version: 2.1
Name: dash-mqtt
Version: 0.0.2
Summary: dash_mqtt is a Dash component library for adding MQTT messaging functionality to your Dash apps.
Home-page: https://github.com/aegis1980/dash-mqtt
Author: Jon Robinson <jonrobinson@hotmail.com>
License: MIT
Platform: UNKNOWN
Classifier: Framework :: Dash
